pyphonic/__init__.py
pyphonic/circular_buffer_overlap.py
pyphonic/flipper.py
pyphonic/functions.py
pyphonic/midi_parser.py
pyphonic/multithreaded_noise.py
pyphonic/preset_10_fftramp.py
pyphonic/preset_11_polysynth.py
pyphonic/preset_12_syncdnoise.py
pyphonic/preset_13_sccompressor.py
pyphonic/preset_14_nn_voice_change.py
pyphonic/preset_15_gen_midi.py
pyphonic/preset_16_gen_drums.py
pyphonic/preset_4_butterworth.py
pyphonic/preset_5_midiarp.py
pyphonic/preset_6_wavetable.py
pyphonic/preset_7_sampler.py
pyphonic/preset_8_noise.py
pyphonic/preset_9_saturator.py
pyphonic-1.1.1.dist-info/LICENSE
pyphonic-1.1.1.dist-info/METADATA
pyphonic-1.1.1.dist-info/WHEEL
pyphonic-1.1.1.dist-info/top_level.txt
pyphonic-1.1.1.dist-info/RECORD
