Metadata-Version: 2.1
Name: pyphonic
Version: 1.1.1
Summary: Make a VST plugin for your DAW using Python
Author-email: Audio Fluff LLC <tom@audiofluff.com>
Project-URL: Homepage, https://github.com/audiofluff/pyphonic
Project-URL: Issues, https://github.com/audiofluff/pyphonic/issues
Classifier: License :: OSI Approved :: MIT License
Classifier: Topic :: Artistic Software
Classifier: Topic :: Multimedia :: Sound/Audio
Classifier: Topic :: Multimedia :: Sound/Audio :: MIDI
Classifier: Topic :: Multimedia :: Sound/Audio :: Sound Synthesis
Classifier: Topic :: Scientific/Engineering :: Artificial Intelligence
Classifier: Programming Language :: Python :: 3
Requires-Python: >=3.8
License-File: LICENSE
